sqlalchemy_theseus_dialect/__init__.py
sqlalchemy_theseus_dialect/sqlalchemy_interfaces.py
sqlalchemy_theseus_dialect-0.0.12.dist-info/LICENSE.txt
sqlalchemy_theseus_dialect-0.0.12.dist-info/METADATA
sqlalchemy_theseus_dialect-0.0.12.dist-info/WHEEL
sqlalchemy_theseus_dialect-0.0.12.dist-info/entry_points.txt
sqlalchemy_theseus_dialect-0.0.12.dist-info/top_level.txt
sqlalchemy_theseus_dialect-0.0.12.dist-info/RECORD
