Metadata-Version: 2.1
Name: sqlalchemy-theseus-dialect
Version: 0.0.12
Summary: A SQLAlchemy dialect for connecting to a Theseus Flight SQL server with ADBC
Author-email: Philip Moore <prmoore77@hotmail.com>
Project-URL: Homepage, https://github.com/prmoore77/sqlalchemy-theseus-dialect
Keywords: sqlalchemy,theseus,gpu,flight-sql,adbc,dialect
Classifier: License :: OSI Approved :: MIT License
Classifier: Programming Language :: Python
Classifier: Programming Language :: Python :: 3
Requires-Python: >=3.9
License-File: LICENSE.txt
Requires-Dist: sqlalchemy ==2.0.*
Requires-Dist: adbc-driver-flightsql ==1.1.*
Requires-Dist: adbc-driver-manager ==1.1.*
Requires-Dist: pyarrow ==17.0.*
Requires-Dist: psycopg2 ==2.9.*
Requires-Dist: importlib-metadata ==8.0.*
Requires-Dist: tenacity ==8.5.*
Provides-Extra: dev
Requires-Dist: bumpver ; extra == 'dev'
Requires-Dist: pip-tools ; extra == 'dev'
Requires-Dist: pytest ; extra == 'dev'
